[
  {
    "name": "Process Start",
    "start": 1611221138428,
    "end": 1611221139162,
    "duration": 734,
    "pid": 77636,
    "index": 0
  },
  {
    "name": "Application Start",
    "start": 1611221139163,
    "end": 1611221140001,
    "duration": 838,
    "pid": 77636,
    "index": 1
  },
  {
    "name": "Load Plugin",
    "start": 1611221139166,
    "end": 1611221139187,
    "duration": 21,
    "pid": 77636,
    "index": 2
  },
  {
    "name": "Load Config",
    "start": 1611221139188,
    "end": 1611221139246,
    "duration": 58,
    "pid": 77636,
    "index": 3
  },
  {
    "name": "Require(0) config/config.default.js",
    "start": 1611221139188,
    "end": 1611221139190,
    "duration": 2,
    "pid": 77636,
    "index": 4
  },
  {
    "name": "Require(1) config/config.local.js",
    "start": 1611221139192,
    "end": 1611221139192,
    "duration": 0,
    "pid": 77636,
    "index": 5
  },
  {
    "name": "Require(2) node_modules/egg-session/config/config.default.js",
    "start": 1611221139192,
    "end": 1611221139194,
    "duration": 2,
    "pid": 77636,
    "index": 6
  },
  {
    "name": "Require(3) node_modules/egg-security/config/config.default.js",
    "start": 1611221139194,
    "end": 1611221139195,
    "duration": 1,
    "pid": 77636,
    "index": 7
  },
  {
    "name": "Require(4) node_modules/egg-jsonp/config/config.default.js",
    "start": 1611221139196,
    "end": 1611221139198,
    "duration": 2,
    "pid": 77636,
    "index": 8
  },
  {
    "name": "Require(5) node_modules/egg-onerror/config/config.default.js",
    "start": 1611221139198,
    "end": 1611221139199,
    "duration": 1,
    "pid": 77636,
    "index": 9
  },
  {
    "name": "Require(6) node_modules/egg-i18n/config/config.default.js",
    "start": 1611221139199,
    "end": 1611221139200,
    "duration": 1,
    "pid": 77636,
    "index": 10
  },
  {
    "name": "Require(7) node_modules/egg-watcher/config/config.default.js",
    "start": 1611221139201,
    "end": 1611221139203,
    "duration": 2,
    "pid": 77636,
    "index": 11
  },
  {
    "name": "Require(8) node_modules/egg-schedule/config/config.default.js",
    "start": 1611221139203,
    "end": 1611221139205,
    "duration": 2,
    "pid": 77636,
    "index": 12
  },
  {
    "name": "Require(9) node_modules/egg-multipart/config/config.default.js",
    "start": 1611221139205,
    "end": 1611221139207,
    "duration": 2,
    "pid": 77636,
    "index": 13
  },
  {
    "name": "Require(10) node_modules/egg-development/config/config.default.js",
    "start": 1611221139207,
    "end": 1611221139208,
    "duration": 1,
    "pid": 77636,
    "index": 14
  },
  {
    "name": "Require(11) node_modules/egg-logrotator/config/config.default.js",
    "start": 1611221139209,
    "end": 1611221139210,
    "duration": 1,
    "pid": 77636,
    "index": 15
  },
  {
    "name": "Require(12) node_modules/egg-static/config/config.default.js",
    "start": 1611221139210,
    "end": 1611221139212,
    "duration": 2,
    "pid": 77636,
    "index": 16
  },
  {
    "name": "Require(13) node_modules/egg-view/config/config.default.js",
    "start": 1611221139212,
    "end": 1611221139214,
    "duration": 2,
    "pid": 77636,
    "index": 17
  },
  {
    "name": "Require(14) node_modules/egg-view-nunjucks/config/config.default.js",
    "start": 1611221139214,
    "end": 1611221139216,
    "duration": 2,
    "pid": 77636,
    "index": 18
  },
  {
    "name": "Require(15) node_modules/egg-sequelize/config/config.default.js",
    "start": 1611221139217,
    "end": 1611221139218,
    "duration": 1,
    "pid": 77636,
    "index": 19
  },
  {
    "name": "Require(16) node_modules/egg-swagger-doc/config/config.default.js",
    "start": 1611221139218,
    "end": 1611221139220,
    "duration": 2,
    "pid": 77636,
    "index": 20
  },
  {
    "name": "Require(17) node_modules/egg-validate/config/config.default.js",
    "start": 1611221139220,
    "end": 1611221139222,
    "duration": 2,
    "pid": 77636,
    "index": 21
  },
  {
    "name": "Require(18) node_modules/egg-redis/config/config.default.js",
    "start": 1611221139223,
    "end": 1611221139224,
    "duration": 1,
    "pid": 77636,
    "index": 22
  },
  {
    "name": "Require(19) node_modules/egg-cors/config/config.default.js",
    "start": 1611221139225,
    "end": 1611221139227,
    "duration": 2,
    "pid": 77636,
    "index": 23
  },
  {
    "name": "Require(20) node_modules/egg-alinode/config/config.default.js",
    "start": 1611221139227,
    "end": 1611221139229,
    "duration": 2,
    "pid": 77636,
    "index": 24
  },
  {
    "name": "Require(21) node_modules/egg/config/config.default.js",
    "start": 1611221139232,
    "end": 1611221139233,
    "duration": 1,
    "pid": 77636,
    "index": 25
  },
  {
    "name": "Require(22) config/config.default.js",
    "start": 1611221139236,
    "end": 1611221139236,
    "duration": 0,
    "pid": 77636,
    "index": 26
  },
  {
    "name": "Require(23) node_modules/egg-security/config/config.local.js",
    "start": 1611221139237,
    "end": 1611221139238,
    "duration": 1,
    "pid": 77636,
    "index": 27
  },
  {
    "name": "Require(24) node_modules/egg-watcher/config/config.local.js",
    "start": 1611221139239,
    "end": 1611221139240,
    "duration": 1,
    "pid": 77636,
    "index": 28
  },
  {
    "name": "Require(25) node_modules/egg-view/config/config.local.js",
    "start": 1611221139241,
    "end": 1611221139242,
    "duration": 1,
    "pid": 77636,
    "index": 29
  },
  {
    "name": "Require(26) node_modules/egg-view-nunjucks/config/config.local.js",
    "start": 1611221139242,
    "end": 1611221139243,
    "duration": 1,
    "pid": 77636,
    "index": 30
  },
  {
    "name": "Require(27) node_modules/egg/config/config.local.js",
    "start": 1611221139245,
    "end": 1611221139246,
    "duration": 1,
    "pid": 77636,
    "index": 31
  },
  {
    "name": "Require(28) config/config.local.js",
    "start": 1611221139246,
    "end": 1611221139246,
    "duration": 0,
    "pid": 77636,
    "index": 32
  },
  {
    "name": "Load extend/application.js",
    "start": 1611221139248,
    "end": 1611221139298,
    "duration": 50,
    "pid": 77636,
    "index": 33
  },
  {
    "name": "Require(29) node_modules/egg-session/app/extend/application.js",
    "start": 1611221139248,
    "end": 1611221139249,
    "duration": 1,
    "pid": 77636,
    "index": 34
  },
  {
    "name": "Require(30) node_modules/egg-security/app/extend/application.js",
    "start": 1611221139249,
    "end": 1611221139251,
    "duration": 2,
    "pid": 77636,
    "index": 35
  },
  {
    "name": "Require(31) node_modules/egg-jsonp/app/extend/application.js",
    "start": 1611221139251,
    "end": 1611221139253,
    "duration": 2,
    "pid": 77636,
    "index": 36
  },
  {
    "name": "Require(32) node_modules/egg-logrotator/app/extend/application.js",
    "start": 1611221139253,
    "end": 1611221139255,
    "duration": 2,
    "pid": 77636,
    "index": 37
  },
  {
    "name": "Require(33) node_modules/egg-view/app/extend/application.js",
    "start": 1611221139256,
    "end": 1611221139259,
    "duration": 3,
    "pid": 77636,
    "index": 38
  },
  {
    "name": "Require(34) node_modules/egg-view-nunjucks/app/extend/application.js",
    "start": 1611221139259,
    "end": 1611221139297,
    "duration": 38,
    "pid": 77636,
    "index": 39
  },
  {
    "name": "Load extend/request.js",
    "start": 1611221139298,
    "end": 1611221139301,
    "duration": 3,
    "pid": 77636,
    "index": 40
  },
  {
    "name": "Require(35) node_modules/egg/app/extend/request.js",
    "start": 1611221139299,
    "end": 1611221139300,
    "duration": 1,
    "pid": 77636,
    "index": 41
  },
  {
    "name": "Load extend/response.js",
    "start": 1611221139301,
    "end": 1611221139306,
    "duration": 5,
    "pid": 77636,
    "index": 42
  },
  {
    "name": "Require(36) node_modules/egg/app/extend/response.js",
    "start": 1611221139302,
    "end": 1611221139305,
    "duration": 3,
    "pid": 77636,
    "index": 43
  },
  {
    "name": "Load extend/context.js",
    "start": 1611221139306,
    "end": 1611221139362,
    "duration": 56,
    "pid": 77636,
    "index": 44
  },
  {
    "name": "Require(37) node_modules/egg-security/app/extend/context.js",
    "start": 1611221139306,
    "end": 1611221139316,
    "duration": 10,
    "pid": 77636,
    "index": 45
  },
  {
    "name": "Require(38) node_modules/egg-jsonp/app/extend/context.js",
    "start": 1611221139316,
    "end": 1611221139318,
    "duration": 2,
    "pid": 77636,
    "index": 46
  },
  {
    "name": "Require(39) node_modules/egg-i18n/app/extend/context.js",
    "start": 1611221139318,
    "end": 1611221139318,
    "duration": 0,
    "pid": 77636,
    "index": 47
  },
  {
    "name": "Require(40) node_modules/egg-multipart/app/extend/context.js",
    "start": 1611221139318,
    "end": 1611221139352,
    "duration": 34,
    "pid": 77636,
    "index": 48
  },
  {
    "name": "Require(41) node_modules/egg-view/app/extend/context.js",
    "start": 1611221139353,
    "end": 1611221139354,
    "duration": 1,
    "pid": 77636,
    "index": 49
  },
  {
    "name": "Require(42) node_modules/egg-swagger-doc/app/extend/context.js",
    "start": 1611221139354,
    "end": 1611221139357,
    "duration": 3,
    "pid": 77636,
    "index": 50
  },
  {
    "name": "Require(43) node_modules/egg-validate/app/extend/context.js",
    "start": 1611221139357,
    "end": 1611221139358,
    "duration": 1,
    "pid": 77636,
    "index": 51
  },
  {
    "name": "Require(44) node_modules/egg/app/extend/context.js",
    "start": 1611221139358,
    "end": 1611221139359,
    "duration": 1,
    "pid": 77636,
    "index": 52
  },
  {
    "name": "Load extend/helper.js",
    "start": 1611221139362,
    "end": 1611221139387,
    "duration": 25,
    "pid": 77636,
    "index": 53
  },
  {
    "name": "Require(45) node_modules/egg-security/app/extend/helper.js",
    "start": 1611221139363,
    "end": 1611221139384,
    "duration": 21,
    "pid": 77636,
    "index": 54
  },
  {
    "name": "Require(46) node_modules/egg/app/extend/helper.js",
    "start": 1611221139385,
    "end": 1611221139385,
    "duration": 0,
    "pid": 77636,
    "index": 55
  },
  {
    "name": "Require(47) app/extend/helper.js",
    "start": 1611221139385,
    "end": 1611221139386,
    "duration": 1,
    "pid": 77636,
    "index": 56
  },
  {
    "name": "Load app.js",
    "start": 1611221139388,
    "end": 1611221139440,
    "duration": 52,
    "pid": 77636,
    "index": 57
  },
  {
    "name": "Require(48) node_modules/egg-session/app.js",
    "start": 1611221139388,
    "end": 1611221139388,
    "duration": 0,
    "pid": 77636,
    "index": 58
  },
  {
    "name": "Require(49) node_modules/egg-security/app.js",
    "start": 1611221139389,
    "end": 1611221139390,
    "duration": 1,
    "pid": 77636,
    "index": 59
  },
  {
    "name": "Require(50) node_modules/egg-onerror/app.js",
    "start": 1611221139391,
    "end": 1611221139400,
    "duration": 9,
    "pid": 77636,
    "index": 60
  },
  {
    "name": "Require(51) node_modules/egg-i18n/app.js",
    "start": 1611221139400,
    "end": 1611221139413,
    "duration": 13,
    "pid": 77636,
    "index": 61
  },
  {
    "name": "Require(52) node_modules/egg-watcher/app.js",
    "start": 1611221139413,
    "end": 1611221139418,
    "duration": 5,
    "pid": 77636,
    "index": 62
  },
  {
    "name": "Require(53) node_modules/egg-schedule/app.js",
    "start": 1611221139418,
    "end": 1611221139420,
    "duration": 2,
    "pid": 77636,
    "index": 63
  },
  {
    "name": "Require(54) node_modules/egg-multipart/app.js",
    "start": 1611221139420,
    "end": 1611221139420,
    "duration": 0,
    "pid": 77636,
    "index": 64
  },
  {
    "name": "Require(55) node_modules/egg-development/app.js",
    "start": 1611221139421,
    "end": 1611221139421,
    "duration": 0,
    "pid": 77636,
    "index": 65
  },
  {
    "name": "Require(56) node_modules/egg-logrotator/app.js",
    "start": 1611221139421,
    "end": 1611221139422,
    "duration": 1,
    "pid": 77636,
    "index": 66
  },
  {
    "name": "Require(57) node_modules/egg-static/app.js",
    "start": 1611221139422,
    "end": 1611221139422,
    "duration": 0,
    "pid": 77636,
    "index": 67
  },
  {
    "name": "Require(58) node_modules/egg-view-nunjucks/app.js",
    "start": 1611221139422,
    "end": 1611221139423,
    "duration": 1,
    "pid": 77636,
    "index": 68
  },
  {
    "name": "Require(59) node_modules/egg-sequelize/app.js",
    "start": 1611221139423,
    "end": 1611221139423,
    "duration": 0,
    "pid": 77636,
    "index": 69
  },
  {
    "name": "Require(60) node_modules/egg-swagger-doc/app.js",
    "start": 1611221139424,
    "end": 1611221139436,
    "duration": 12,
    "pid": 77636,
    "index": 70
  },
  {
    "name": "Require(61) node_modules/egg-validate/app.js",
    "start": 1611221139436,
    "end": 1611221139437,
    "duration": 1,
    "pid": 77636,
    "index": 71
  },
  {
    "name": "Require(62) node_modules/egg-redis/app.js",
    "start": 1611221139438,
    "end": 1611221139439,
    "duration": 1,
    "pid": 77636,
    "index": 72
  },
  {
    "name": "Require(63) node_modules/egg-cors/app.js",
    "start": 1611221139439,
    "end": 1611221139439,
    "duration": 0,
    "pid": 77636,
    "index": 73
  },
  {
    "name": "Before Start in node_modules/egg-watcher/lib/init.js:15:14",
    "start": 1611221139446,
    "end": 1611221139991,
    "duration": 545,
    "pid": 77636,
    "index": 74
  },
  {
    "name": "Load \"Symbol(model)\" to Application",
    "start": 1611221139757,
    "end": 1611221139767,
    "duration": 10,
    "pid": 77636,
    "index": 75
  },
  {
    "name": "Before Start in node_modules/egg-sequelize/lib/loader.js:39:7",
    "start": 1611221139767,
    "end": 1611221140001,
    "duration": 234,
    "pid": 77636,
    "index": 76
  },
  {
    "name": "Before Start in node_modules/egg-swagger-doc/app.js:6:7",
    "start": 1611221139767,
    "end": 1611221139964,
    "duration": 197,
    "pid": 77636,
    "index": 77
  },
  {
    "name": "Before Start in node_modules/egg-redis/lib/redis.js:53:7",
    "start": 1611221139811,
    "end": 1611221139977,
    "duration": 166,
    "pid": 77636,
    "index": 78
  },
  {
    "name": "Load Service",
    "start": 1611221139811,
    "end": 1611221139818,
    "duration": 7,
    "pid": 77636,
    "index": 79
  },
  {
    "name": "Load \"service\" to Context",
    "start": 1611221139811,
    "end": 1611221139818,
    "duration": 7,
    "pid": 77636,
    "index": 80
  },
  {
    "name": "Load Middleware",
    "start": 1611221139818,
    "end": 1611221139892,
    "duration": 74,
    "pid": 77636,
    "index": 81
  },
  {
    "name": "Load \"middlewares\" to Application",
    "start": 1611221139818,
    "end": 1611221139878,
    "duration": 60,
    "pid": 77636,
    "index": 82
  },
  {
    "name": "Load Controller",
    "start": 1611221139892,
    "end": 1611221139897,
    "duration": 5,
    "pid": 77636,
    "index": 83
  },
  {
    "name": "Load \"controller\" to Application",
    "start": 1611221139892,
    "end": 1611221139897,
    "duration": 5,
    "pid": 77636,
    "index": 84
  },
  {
    "name": "Load Router",
    "start": 1611221139897,
    "end": 1611221139900,
    "duration": 3,
    "pid": 77636,
    "index": 85
  },
  {
    "name": "Require(64) app/router.js",
    "start": 1611221139897,
    "end": 1611221139898,
    "duration": 1,
    "pid": 77636,
    "index": 86
  },
  {
    "name": "Before Start in node_modules/egg-core/lib/egg.js:303:10",
    "start": 1611221139898,
    "end": 1611221139964,
    "duration": 66,
    "pid": 77636,
    "index": 87
  }
]